sky/__init__.py
sky/admin_policy.py
sky/authentication.py
sky/check.py
sky/cli.py
sky/cloud_stores.py
sky/core.py
sky/dag.py
sky/exceptions.py
sky/execution.py
sky/global_user_state.py
sky/optimizer.py
sky/resources.py
sky/sky_logging.py
sky/skypilot_config.py
sky/status_lib.py
sky/task.py
sky/adaptors/__init__.py
sky/adaptors/aws.py
sky/adaptors/azure.py
sky/adaptors/cloudflare.py
sky/adaptors/common.py
sky/adaptors/cudo.py
sky/adaptors/docker.py
sky/adaptors/gcp.py
sky/adaptors/ibm.py
sky/adaptors/kubernetes.py
sky/adaptors/oci.py
sky/adaptors/runpod.py
sky/adaptors/vsphere.py
sky/backends/__init__.py
sky/backends/backend.py
sky/backends/backend_utils.py
sky/backends/cloud_vm_ray_backend.py
sky/backends/docker_utils.py
sky/backends/local_docker_backend.py
sky/backends/wheel_utils.py
sky/backends/monkey_patches/monkey_patch_ray_up.py
sky/benchmark/__init__.py
sky/benchmark/benchmark_state.py
sky/benchmark/benchmark_utils.py
sky/clouds/__init__.py
sky/clouds/aws.py
sky/clouds/azure.py
sky/clouds/cloud.py
sky/clouds/cloud_registry.py
sky/clouds/cudo.py
sky/clouds/fluidstack.py
sky/clouds/gcp.py
sky/clouds/ibm.py
sky/clouds/kubernetes.py
sky/clouds/lambda_cloud.py
sky/clouds/oci.py
sky/clouds/paperspace.py
sky/clouds/runpod.py
sky/clouds/scp.py
sky/clouds/vsphere.py
sky/clouds/service_catalog/__init__.py
sky/clouds/service_catalog/aws_catalog.py
sky/clouds/service_catalog/azure_catalog.py
sky/clouds/service_catalog/common.py
sky/clouds/service_catalog/config.py
sky/clouds/service_catalog/constants.py
sky/clouds/service_catalog/cudo_catalog.py
sky/clouds/service_catalog/fluidstack_catalog.py
sky/clouds/service_catalog/gcp_catalog.py
sky/clouds/service_catalog/ibm_catalog.py
sky/clouds/service_catalog/kubernetes_catalog.py
sky/clouds/service_catalog/lambda_catalog.py
sky/clouds/service_catalog/oci_catalog.py
sky/clouds/service_catalog/paperspace_catalog.py
sky/clouds/service_catalog/runpod_catalog.py
sky/clouds/service_catalog/scp_catalog.py
trainy_skypilot_nightly-1.0.0.dev20250704.dist-info/licenses/LICENSE
trainy_skypilot_nightly-1.0.0.dev20250704.dist-info/METADATA
trainy_skypilot_nightly-1.0.0.dev20250704.dist-info/WHEEL
trainy_skypilot_nightly-1.0.0.dev20250704.dist-info/entry_points.txt
trainy_skypilot_nightly-1.0.0.dev20250704.dist-info/top_level.txt
trainy_skypilot_nightly-1.0.0.dev20250704.dist-info/RECORD
